hydra_plugins/hydra_aws_batch_launcher/__init__.py
hydra_plugins/hydra_aws_batch_launcher/aws_batch_launcher.py
hydra_plugins/hydra_aws_batch_launcher/config.py
hydra_aws_batch_launcher-1.3.1.dist-info/LICENSE
hydra_aws_batch_launcher-1.3.1.dist-info/METADATA
hydra_aws_batch_launcher-1.3.1.dist-info/WHEEL
hydra_aws_batch_launcher-1.3.1.dist-info/top_level.txt
hydra_aws_batch_launcher-1.3.1.dist-info/RECORD
