Metadata-Version: 2.1
Name: hydra-aws-batch-launcher
Version: 1.3.1
Summary: AWS Batcher Launcher for Hydra apps
Home-page: https://github.com/philkohl/hydra_aws_batch_launcher/
Author: philkohl
Author-email: 65112414+philkohl@users.noreply.github.com
Classifier: License :: OSI Approved :: MIT License
Classifier: Programming Language :: Python :: 3.8
Classifier: Programming Language :: Python :: 3.9
Classifier: Programming Language :: Python :: 3.10
Classifier: Programming Language :: Python :: 3.11
Classifier: Operating System :: MacOS
Classifier: Operating System :: Microsoft :: Windows
Classifier: Operating System :: POSIX :: Linux
License-File: LICENSE
Requires-Dist: hydra-core>=1.3.2
